{
  "id": "MAP_MT_EMBER_SUMMIT_PATH_1F",
  "metadata": {
    "name": "MtEmber_SummitPath_1F",
    "layout": "LAYOUT_MT_EMBER_SUMMIT_PATH_1F",
    "music": "MUS_SEVII_CAVE",
    "regionMapSection": "MAPSEC_MT_EMBER",
    "weather": "WEATHER_NONE",
    "mapType": "MAP_TYPE_UNDERGROUND",
    "allowCycling": true,
    "allowEscaping": true,
    "allowRunning": true,
    "showMapName": true,
    "battleScene": "MAP_BATTLE_SCENE_NORMAL",
    "connections": null
  },
  "wildEncounters": {
    "land": {
      "encounterRate": 7,
      "mons": [
        {
          "minLevel": 33,
          "maxLevel": 33,
          "species": "SPECIES_GEODUDE",
          "slotRate": 20
        },
        {
          "minLevel": 35,
          "maxLevel": 35,
          "species": "SPECIES_MACHOP",
          "slotRate": 20
        },
        {
          "minLevel": 29,
          "maxLevel": 29,
          "species": "SPECIES_GEODUDE",
          "slotRate": 10
        },
        {
          "minLevel": 31,
          "maxLevel": 31,
          "species": "SPECIES_GEODUDE",
          "slotRate": 10
        },
        {
          "minLevel": 31,
          "maxLevel": 31,
          "species": "SPECIES_MACHOP",
          "slotRate": 10
        },
        {
          "minLevel": 33,
          "maxLevel": 33,
          "species": "SPECIES_MACHOP",
          "slotRate": 10
        },
        {
          "minLevel": 35,
          "maxLevel": 35,
          "species": "SPECIES_GEODUDE",
          "slotRate": 5
        },
        {
          "minLevel": 37,
          "maxLevel": 37,
          "species": "SPECIES_MACHOP",
          "slotRate": 5
        },
        {
          "minLevel": 37,
          "maxLevel": 37,
          "species": "SPECIES_GEODUDE",
          "slotRate": 4
        },
        {
          "minLevel": 39,
          "maxLevel": 39,
          "species": "SPECIES_MACHOP",
          "slotRate": 4
        },
        {
          "minLevel": 37,
          "maxLevel": 37,
          "species": "SPECIES_GEODUDE",
          "slotRate": 1
        },
        {
          "minLevel": 39,
          "maxLevel": 39,
          "species": "SPECIES_MACHOP",
          "slotRate": 1
        }
      ]
    }
  },
  "width": 15,
  "height": 18,
  "tileSize": 16,
  "visual": {
    "primaryTileset": "general",
    "secondaryTileset": "mt_ember",
    "metatileIds": [
      657,
      657,
      657,
      657,
      657,
      657,
      657,
      719,
      667,
      708,
      651,
      652,
      653,
      708,
      668,
      657,
      657,
      657,
      657,
      657,
      719,
      657,
      657,
      711,
      667,
      659,
      660,
      661,
      668,
      710,
      657,
      657,
      657,
      809,
      667,
      708,
      708,
      708,
      666,
      658,
      801,
      641,
      641,
      656,
      710,
      657,
      657,
      657,
      657,
      711,
      667,
      665,
      665,
      665,
      666,
      641,
      641,
      803,
      656,
      710,
      657,
      657,
      667,
      708,
      666,
      658,
      641,
      641,
      641,
      641,
      641,
      641,
      648,
      649,
      710,
      811,
      719,
      711,
      667,
      665,
      666,
      641,
      648,
      649,
      649,
      649,
      649,
      649,
      672,
      649,
      667,
      708,
      666,
      658,
      641,
      641,
      641,
      656,
      672,
      649,
      649,
      810,
      649,
      649,
      657,
      711,
      667,
      665,
      666,
      641,
      648,
      649,
      649,
      710,
      657,
      657,
      657,
      657,
      719,
      657,
      711,
      658,
      641,
      641,
      641,
      656,
      672,
      649,
      649,
      719,
      657,
      657,
      657,
      657,
      657,
      711,
      658,
      641,
      648,
      649,
      649,
      710,
      657,
      657,
      657,
      657,
      657,
      657,
      657,
      657,
      711,
      658,
      641,
      656,
      672,
      649,
      649,
      657,
      657,
      657,
      657,
      657,
      657,
      657,
      657,
      711,
      658,
      641,
      656,
      710,
      657,
      657,
      657,
      657,
      657,
      657,
      657,
      657,
      657,
      657,
      711,
      658,
      641,
      656,
      710,
      809,
      657,
      657,
      657,
      657,
      657,
      657,
      657,
      657,
      657,
      711,
      658,
      641,
      656,
      710,
      657,
      657,
      657,
      657,
      657,
      657,
      657,
      657,
      657,
      657,
      711,
      658,
      641,
      656,
      710,
      657,
      719,
      657,
      657,
      657,
      657,
      657,
      657,
      657,
      657,
      711,
      658,
      647,
      656,
      710,
      657,
      657,
      657,
      657,
      657,
      657,
      657,
      657,
      657,
      657,
      711,
      712,
      713,
      714,
      710,
      657,
      657,
      657,
      657,
      657,
      657,
      657,
      657,
      657,
      657,
      649,
      727,
      649,
      649,
      649,
      719,
      657,
      657,
      657,
      657,
      657,
      657,
      657,
      657,
      657
    ],
    "layerTypes": [
      1,
      1,
      1,
      1,
      1,
      1,
      1,
      0,
      0,
      1,
      0,
      0,
      0,
      1,
      0,
      1,
      1,
      1,
      1,
      1,
      0,
      1,
      1,
      1,
      0,
      0,
      0,
      0,
      0,
      1,
      1,
      1,
      1,
      0,
      0,
      1,
      1,
      1,
      1,
      1,
      0,
      0,
      0,
      1,
      1,
      1,
      1,
      1,
      1,
      1,
      0,
      1,
      1,
      1,
      1,
      0,
      0,
      0,
      1,
      1,
      1,
      1,
      0,
      1,
      1,
      1,
      0,
      0,
      0,
      0,
      0,
      0,
      1,
      1,
      1,
      0,
      0,
      1,
      0,
      1,
      1,
      0,
      1,
      1,
      1,
      1,
      1,
      1,
      1,
      1,
      0,
      1,
      1,
      1,
      0,
      0,
      0,
      1,
      1,
      1,
      1,
      0,
      1,
      1,
      1,
      1,
      0,
      1,
      1,
      0,
      1,
      1,
      1,
      1,
      1,
      1,
      1,
      1,
      0,
      1,
      1,
      1,
      0,
      0,
      0,
      1,
      1,
      1,
      1,
      0,
      1,
      1,
      1,
      1,
      1,
      1,
      1,
      0,
      1,
      1,
      1,
      1,
      1,
      1,
      1,
      1,
      1,
      1,
      1,
      1,
      1,
      1,
      0,
      1,
      1,
      1,
      1,
      1,
      1,
      1,
      1,
      1,
      1,
      1,
      1,
      1,
      1,
      0,
      1,
      1,
      1,
      1,
      1,
      1,
      1,
      1,
      1,
      1,
      1,
      1,
      1,
      1,
      0,
      1,
      1,
      0,
      1,
      1,
      1,
      1,
      1,
      1,
      1,
      1,
      1,
      1,
      1,
      0,
      1,
      1,
      1,
      1,
      1,
      1,
      1,
      1,
      1,
      1,
      1,
      1,
      1,
      1,
      0,
      1,
      1,
      1,
      0,
      1,
      1,
      1,
      1,
      1,
      1,
      1,
      1,
      1,
      1,
      0,
      1,
      1,
      1,
      1,
      1,
      1,
      1,
      1,
      1,
      1,
      1,
      1,
      1,
      1,
      1,
      1,
      1,
      1,
      1,
      1,
      1,
      1,
      1,
      1,
      1,
      1,
      1,
      1,
      0,
      1,
      1,
      1,
      0,
      1,
      1,
      1,
      1,
      1,
      1,
      1,
      1,
      1
    ]
  },
  "collisionRows": [
    "111111111111111",
    "111111111110111",
    "111111111100011",
    "111111111100011",
    "111111000000111",
    "111111011111111",
    "111100011111111",
    "111101111111111",
    "110001111111111",
    "110111111111111",
    "110111111111111",
    "110111111111111",
    "110111111111111",
    "110111111111111",
    "110111111111111",
    "110111111111111",
    "111111111111111",
    "111111111111111"
  ],
  "encounterRows": [
    "LLLLLLLL.L...L.",
    "LLLLLLLLL.....L",
    "LLL..LLL..LLL.L",
    "LLLLL.....LLL.L",
    "LL.L..LLLLLL.LL",
    ".LL...L.LLLLL.L",
    ".L..LLL..LL.LLL",
    "L...L.LLLLLLLLL",
    "L.LLL..LLLLLLLL",
    "L.L.LLLLLLLLLLL",
    "L.L..LLLLLLLLLL",
    "L.L.LLLLLLLLLLL",
    "L.L.L.LLLLLLLLL",
    "L.L.LLLLLLLLLLL",
    "L.L.LLLLLLLLLLL",
    "L.L.LLLLLLLLLLL",
    "LLLLLLLLLLLLLLL",
    "LLLLLLLLLLLLLLL"
  ],
  "elevationRows": [
    "000000000000000",
    "000000000003000",
    "000000000033300",
    "000000000033300",
    "000000333333000",
    "000000300000000",
    "000033300000000",
    "000030000000000",
    "003330000000000",
    "003000000000000",
    "003000000000000",
    "003000000000000",
    "003000000000000",
    "003000000000000",
    "003000000000000",
    "003000000000000",
    "000000000000000",
    "000000000000000"
  ],
  "behaviorRows": [
    "080808080808080000000000000000",
    "080808080800080800000060000000",
    "080808000000000000000808080000",
    "080808080000000000000808080000",
    "080800000000080808080808003200",
    "000000000000080032323232320032",
    "000000000808080000323200323208",
    "000000000800323200080808080008",
    "000008080800003232000808080808",
    "000008003232000808080808080808",
    "000008000032320808080808080808",
    "000008000008080808080808080808",
    "000008000000080808080808080808",
    "000008000008080808080808080808",
    "000008000008000808080808080808",
    "000065000008080808080808080808",
    "000000000008080808080808080808",
    "320032323200080808080808080808"
  ],
  "terrainRows": [
    "000000000000000",
    "000000000000000",
    "000000000000000",
    "000000000000000",
    "000000000000000",
    "000000000000000",
    "000000000000000",
    "000000000000000",
    "000000000000000",
    "000000000000000",
    "000000000000000",
    "000000000000000",
    "000000000000000",
    "000000000000000",
    "000000000000000",
    "000000000000000",
    "000000000000000",
    "000000000000000"
  ],
  "triggers": [],
  "warps": [
    {
      "x": 2,
      "y": 15,
      "elevation": 0,
      "destMap": "MAP_MT_EMBER_EXTERIOR",
      "destWarpId": 2
    },
    {
      "x": 11,
      "y": 1,
      "elevation": 0,
      "destMap": "MAP_MT_EMBER_SUMMIT_PATH_2F",
      "destWarpId": 0
    }
  ],
  "hiddenItems": [],
  "berryTrees": [],
  "cloneObjects": [],
  "npcs": []
}
