{
  "id": "MAP_SAFARI_ZONE_EAST_REST_HOUSE",
  "metadata": {
    "name": "SafariZone_East_RestHouse",
    "layout": "LAYOUT_SAFARI_ZONE_REST_HOUSE",
    "music": "MUS_EVOLUTION",
    "regionMapSection": "MAPSEC_KANTO_SAFARI_ZONE",
    "weather": "WEATHER_NONE",
    "mapType": "MAP_TYPE_INDOOR",
    "allowCycling": false,
    "allowEscaping": false,
    "allowRunning": false,
    "showMapName": false,
    "battleScene": "MAP_BATTLE_SCENE_NORMAL",
    "connections": null
  },
  "width": 13,
  "height": 11,
  "tileSize": 16,
  "visual": {
    "primaryTileset": "building",
    "secondaryTileset": "safari_zone_building",
    "metatileIds": [
      641,
      641,
      641,
      641,
      641,
      641,
      641,
      641,
      641,
      680,
      681,
      680,
      681,
      654,
      654,
      649,
      649,
      649,
      649,
      649,
      654,
      654,
      688,
      689,
      688,
      689,
      662,
      662,
      664,
      664,
      664,
      664,
      664,
      662,
      662,
      696,
      697,
      696,
      697,
      664,
      656,
      656,
      656,
      656,
      656,
      656,
      656,
      656,
      656,
      656,
      656,
      656,
      664,
      656,
      657,
      656,
      656,
      657,
      656,
      656,
      656,
      656,
      656,
      656,
      656,
      664,
      656,
      656,
      656,
      656,
      656,
      656,
      656,
      661,
      669,
      669,
      669,
      669,
      664,
      656,
      656,
      656,
      656,
      656,
      656,
      656,
      694,
      677,
      677,
      699,
      699,
      664,
      656,
      657,
      656,
      656,
      657,
      656,
      656,
      668,
      685,
      686,
      687,
      687,
      664,
      656,
      656,
      656,
      656,
      656,
      656,
      656,
      668,
      693,
      698,
      671,
      671,
      664,
      656,
      656,
      682,
      683,
      684,
      656,
      656,
      676,
      693,
      678,
      678,
      678,
      8,
      8,
      8,
      26,
      27,
      28,
      8,
      8,
      8,
      8,
      8,
      8,
      8
    ],
    "layerTypes": [
      0,
      0,
      0,
      0,
      0,
      0,
      0,
      0,
      0,
      1,
      1,
      1,
      1,
      0,
      0,
      0,
      0,
      0,
      0,
      0,
      0,
      0,
      1,
      1,
      1,
      1,
      1,
      1,
      0,
      0,
      0,
      0,
      0,
      1,
      1,
      1,
      1,
      1,
      1,
      0,
      0,
      0,
      0,
      0,
      0,
      0,
      0,
      0,
      0,
      0,
      0,
      0,
      0,
      0,
      1,
      0,
      0,
      1,
      0,
      0,
      0,
      0,
      0,
      0,
      0,
      0,
      0,
      0,
      0,
      0,
      0,
      0,
      0,
      0,
      0,
      0,
      0,
      0,
      0,
      0,
      0,
      0,
      0,
      0,
      0,
      0,
      1,
      1,
      1,
      1,
      1,
      0,
      0,
      1,
      0,
      0,
      1,
      0,
      0,
      1,
      0,
      0,
      1,
      1,
      0,
      0,
      0,
      0,
      0,
      0,
      0,
      0,
      1,
      0,
      1,
      1,
      1,
      0,
      0,
      0,
      1,
      1,
      1,
      0,
      0,
      1,
      0,
      1,
      1,
      1,
      0,
      0,
      0,
      1,
      1,
      1,
      0,
      0,
      0,
      0,
      0,
      0,
      0
    ]
  },
  "collisionRows": [
    "1111111111111",
    "1111111111111",
    "1100000110000",
    "0000000000000",
    "0000000000000",
    "0000000000000",
    "0000000011111",
    "0000000010011",
    "0000000010111",
    "0000000010111",
    "1111111111111"
  ],
  "encounterRows": [
    ".............",
    ".............",
    ".............",
    ".............",
    ".............",
    ".............",
    ".............",
    ".............",
    ".............",
    ".............",
    "............."
  ],
  "elevationRows": [
    "0000000000000",
    "0000000000000",
    "0033333003333",
    "3333333333333",
    "3333333333333",
    "3333333333333",
    "3333333300000",
    "3333333303300",
    "3333333303000",
    "3333333303000",
    "0000000000000"
  ],
  "behaviorRows": [
    "00000000000000000000000000",
    "00000000000000000081818181",
    "00000000000000000000000000",
    "00000000000000000000000000",
    "00000000000000000000000000",
    "00000000000000000000000000",
    "00000000000000008080800000",
    "00000000000000008000000000",
    "00000000000000008000000000",
    "00000000650000008000000000",
    "00000000000000000000000000"
  ],
  "terrainRows": [
    "0000000000000",
    "0000000000000",
    "0000000000000",
    "0000000000000",
    "0000000000000",
    "0000000000000",
    "0000000000000",
    "0000000000000",
    "0000000000000",
    "0000000000000",
    "0000000000000"
  ],
  "triggers": [],
  "warps": [
    {
      "x": 3,
      "y": 9,
      "elevation": 3,
      "destMap": "MAP_SAFARI_ZONE_EAST",
      "destWarpId": 6
    },
    {
      "x": 4,
      "y": 9,
      "elevation": 3,
      "destMap": "MAP_SAFARI_ZONE_EAST",
      "destWarpId": 6
    },
    {
      "x": 5,
      "y": 9,
      "elevation": 3,
      "destMap": "MAP_SAFARI_ZONE_EAST",
      "destWarpId": 6
    }
  ],
  "hiddenItems": [],
  "berryTrees": [],
  "cloneObjects": [],
  "npcs": [
    {
      "id": "SafariZone_East_RestHouse_ObjectEvent_Scientist",
      "x": 3,
      "y": 5,
      "graphicsId": "OBJ_EVENT_GFX_SCIENTIST",
      "movementType": "MOVEMENT_TYPE_LOOK_AROUND",
      "movementRangeX": 1,
      "movementRangeY": 1,
      "trainerType": "TRAINER_TYPE_NONE",
      "trainerSightOrBerryTreeId": 0,
      "scriptId": "SafariZone_East_RestHouse_EventScript_Scientist",
      "flag": "0"
    },
    {
      "id": "SafariZone_East_RestHouse_ObjectEvent_Rocker",
      "x": 6,
      "y": 3,
      "graphicsId": "OBJ_EVENT_GFX_ROCKER",
      "movementType": "MOVEMENT_TYPE_FACE_DOWN",
      "movementRangeX": 1,
      "movementRangeY": 1,
      "trainerType": "TRAINER_TYPE_NONE",
      "trainerSightOrBerryTreeId": 0,
      "scriptId": "SafariZone_East_RestHouse_EventScript_Rocker",
      "flag": "0"
    },
    {
      "id": "SafariZone_East_RestHouse_ObjectEvent_BaldingMan",
      "x": 7,
      "y": 3,
      "graphicsId": "OBJ_EVENT_GFX_BALDING_MAN",
      "movementType": "MOVEMENT_TYPE_FACE_DOWN",
      "movementRangeX": 1,
      "movementRangeY": 1,
      "trainerType": "TRAINER_TYPE_NONE",
      "trainerSightOrBerryTreeId": 0,
      "scriptId": "SafariZone_East_RestHouse_EventScript_BaldingMan",
      "flag": "0"
    }
  ]
}
