{
  "id": "MAP_SIX_ISLAND_WATER_PATH_HOUSE1",
  "metadata": {
    "name": "SixIsland_WaterPath_House1",
    "layout": "LAYOUT_HOUSE4",
    "music": "MUS_FUCHSIA",
    "regionMapSection": "MAPSEC_WATER_PATH",
    "weather": "WEATHER_NONE",
    "mapType": "MAP_TYPE_INDOOR",
    "allowCycling": false,
    "allowEscaping": false,
    "allowRunning": false,
    "showMapName": false,
    "battleScene": "MAP_BATTLE_SCENE_NORMAL",
    "connections": null
  },
  "width": 11,
  "height": 9,
  "tileSize": 16,
  "visual": {
    "primaryTileset": "building",
    "secondaryTileset": "generic_building_2",
    "metatileIds": [
      270,
      268,
      269,
      264,
      280,
      352,
      280,
      352,
      264,
      260,
      264,
      278,
      276,
      277,
      272,
      288,
      360,
      288,
      360,
      272,
      261,
      272,
      286,
      284,
      285,
      273,
      273,
      273,
      273,
      273,
      273,
      273,
      273,
      273,
      265,
      265,
      265,
      265,
      265,
      265,
      265,
      265,
      265,
      265,
      342,
      265,
      265,
      265,
      367,
      357,
      358,
      359,
      265,
      265,
      265,
      350,
      265,
      265,
      265,
      367,
      365,
      366,
      359,
      265,
      265,
      265,
      342,
      265,
      265,
      265,
      265,
      265,
      265,
      265,
      265,
      265,
      265,
      350,
      265,
      319,
      327,
      335,
      265,
      265,
      265,
      265,
      265,
      265,
      8,
      8,
      26,
      27,
      28,
      8,
      8,
      8,
      8,
      8,
      8
    ],
    "layerTypes": [
      1,
      1,
      1,
      0,
      1,
      1,
      1,
      1,
      0,
      1,
      0,
      1,
      1,
      1,
      0,
      1,
      1,
      1,
      1,
      0,
      1,
      0,
      1,
      1,
      1,
      0,
      0,
      0,
      0,
      0,
      0,
      0,
      0,
      0,
      0,
      0,
      0,
      0,
      0,
      0,
      0,
      0,
      0,
      0,
      0,
      0,
      0,
      0,
      1,
      1,
      1,
      1,
      0,
      0,
      0,
      1,
      0,
      0,
      0,
      1,
      1,
      1,
      1,
      0,
      0,
      0,
      0,
      0,
      0,
      0,
      0,
      0,
      0,
      0,
      0,
      0,
      0,
      1,
      0,
      1,
      1,
      1,
      0,
      0,
      0,
      0,
      0,
      0,
      0,
      0,
      1,
      1,
      1,
      0,
      0,
      0,
      0,
      0,
      0
    ]
  },
  "collisionRows": [
    "11111111111",
    "11111111111",
    "00000000000",
    "00000000000",
    "00000110000",
    "10000110000",
    "00000000000",
    "10000000000",
    "11111111111"
  ],
  "encounterRows": [
    "...........",
    "...........",
    "...........",
    "...........",
    "...........",
    "...........",
    "...........",
    "...........",
    "..........."
  ],
  "elevationRows": [
    "00000000000",
    "00000000000",
    "33333333333",
    "33333333333",
    "33333003333",
    "03333003333",
    "33333333333",
    "03333333333",
    "00000000000"
  ],
  "behaviorRows": [
    "0000000000000000000000",
    "81898900009d009d000000",
    "0000000000000000000000",
    "0000000000000000000000",
    "0000000000000000000000",
    "0000000000000000000000",
    "0000000000000000000000",
    "0000006500000000000000",
    "0000000000000000000000"
  ],
  "terrainRows": [
    "00000000000",
    "00000000000",
    "00000000000",
    "00000000000",
    "00000000000",
    "00000000000",
    "00000000000",
    "00000000000",
    "00000000000"
  ],
  "triggers": [
    {
      "id": "SixIsland_WaterPath_House1_EventScript_SizeRecord",
      "x": 9,
      "y": 1,
      "elevation": 0,
      "activation": "interact",
      "scriptId": "SixIsland_WaterPath_House1_EventScript_SizeRecord",
      "facing": "any",
      "once": false
    }
  ],
  "warps": [
    {
      "x": 3,
      "y": 7,
      "elevation": 3,
      "destMap": "MAP_SIX_ISLAND_WATER_PATH",
      "destWarpId": 0
    }
  ],
  "hiddenItems": [],
  "berryTrees": [],
  "cloneObjects": [],
  "npcs": [
    {
      "id": "SixIsland_WaterPath_House1_ObjectEvent_Beauty",
      "x": 3,
      "y": 4,
      "graphicsId": "OBJ_EVENT_GFX_BEAUTY",
      "movementType": "MOVEMENT_TYPE_FACE_DOWN",
      "movementRangeX": 1,
      "movementRangeY": 1,
      "trainerType": "TRAINER_TYPE_NONE",
      "trainerSightOrBerryTreeId": 0,
      "scriptId": "SixIsland_WaterPath_House1_EventScript_Beauty",
      "flag": "0"
    }
  ]
}
